[{"name":"Granlund","team":"Örebro SK","points":"71","cost":"5,2","oldCost":"5,3"},{"name":"Calisir","team":"IFK Göteborg","points":"95","cost":"4,9","oldCost":"5,0"},{"name":"Wikström","team":"IFK Göteborg","points":"2","cost":"3,8","oldCost":"3,9"},{"name":"Aiesh","team":"IFK Göteborg","points":"96","cost":"9,3","oldCost":"9,2"},{"name":"Irandust","team":"BK Häcken","points":"110","cost":"9,3","oldCost":"9,4"},{"name":"Ring","team":"Djurgårdens IF","points":"142","cost":"8,1","oldCost":"8,0"},{"name":"Bojanic","team":"Hammarby IF","points":"130","cost":"7,4","oldCost":"7,3"},{"name":"Friberg","team":"BK Häcken","points":"89","cost":"6,8","oldCost":"6,9"},{"name":"Yakob","team":"BK Häcken","points":"0","cost":"4,7","oldCost":"4,8"},{"name":"Nilsson","team":"BK Häcken","points":"13","cost":"8,1","oldCost":"8,2"}]